strassen_attention/__init__.py
strassen_attention/strassen_attention.py
strassen_attention/strassen_mha.py
strassen_attention/strassen_transformer.py
strassen_attention-0.1.5.dist-info/METADATA
strassen_attention-0.1.5.dist-info/WHEEL
strassen_attention-0.1.5.dist-info/licenses/LICENSE
strassen_attention-0.1.5.dist-info/RECORD
